{
  "pageSize": 25,
  "pageNumber": 1,
  "pageCount": 2,
  "result": [
    {
      "classType": "Atom",
      "ui": "A35373398",
      "sourceDescriptor": "https://uts-ws.nlm.nih.gov/rest/content/2026AA/source/MDRARA/10012601",
      "sourceConcept": "NONE",
      "concept": "https://uts-ws.nlm.nih.gov/rest/content/2026AA/CUI/C0235397",
      "suppressible": "false",
      "obsolete": "false",
      "rootSource": "MDRARA",
      "termType": "LLT",
      "code": "https://uts-ws.nlm.nih.gov/rest/content/2026AA/source/MDRARA/10012620",
      "language": "ARA",
      "name": "مرض السكري المترسب",
      "ancestors": "NONE",
      "descendants": "NONE",
      "attributes": "NONE",
      "relations": "https://uts-ws.nlm.nih.gov/rest/content/2026AA/AUI/A35373398/relations",
      "children": "NONE",
      "parents": "NONE"
    },
    {
      "classType": "Atom",
      "ui": "A29961935",
      "sourceDescriptor": "https://uts-ws.nlm.nih.gov/rest/content/2026AA/source/MDRCZE/10012601",
      "sourceConcept": "NONE",
      "concept": "https://uts-ws.nlm.nih.gov/rest/content/2026AA/CUI/C0235397",
      "suppressible": "false",
      "obsolete": "false",
      "rootSource": "MDRCZE",
      "termType": "LLT",
      "code": "https://uts-ws.nlm.nih.gov/rest/content/2026AA/source/MDRCZE/10012620",
      "language": "CZE",
      "name": "Sekundární diabetes mellitus",
      "ancestors": "NONE",
      "descendants": "NONE",
      "attributes": "NONE",
      "relations": "https://uts-ws.nlm.nih.gov/rest/content/2026AA/AUI/A29961935/relations",
      "children": "NONE",
      "parents": "NONE"
    },
    {
      "classType": "Atom",
      "ui": "A25829149",
      "sourceDescriptor": "https://uts-ws.nlm.nih.gov/rest/content/2026AA/source/MDRDUT/10012601",
      "sourceConcept": "NONE",
      "concept": "https://uts-ws.nlm.nih.gov/rest/content/2026AA/CUI/C0235397",
      "suppressible": "false",
      "obsolete": "false",
      "rootSource": "MDRDUT",
      "termType": "LLT",
      "code": "https://uts-ws.nlm.nih.gov/rest/content/2026AA/source/MDRDUT/10012620",
      "language": "DUT",
      "name": "onverwachte diabetes mellitus",
      "ancestors": "NONE",
      "descendants": "NONE",
      "attributes": "NONE",
      "relations": "https://uts-ws.nlm.nih.gov/rest/content/2026AA/AUI/A25829149/relations",
      "children": "NONE",
      "parents": "NONE"
    },
    {
      "classType": "Atom",
      "ui": "A25684436",
      "sourceDescriptor": "https://uts-ws.nlm.nih.gov/rest/content/2026AA/source/MDR/10012601",
      "sourceConcept": "NONE",
      "concept": "https://uts-ws.nlm.nih.gov/rest/content/2026AA/CUI/C0235397",
      "suppressible": "false",
      "obsolete": "false",
      "rootSource": "MDR",
      "termType": "LLT",
      "code": "https://uts-ws.nlm.nih.gov/rest/content/2026AA/source/MDR/10012620",
      "language": "ENG",
      "name": "Diabetes mellitus precipitated",
      "ancestors": "NONE",
      "descendants": "NONE",
      "attributes": "NONE",
      "relations": "https://uts-ws.nlm.nih.gov/rest/content/2026AA/AUI/A25684436/relations",
      "children": "NONE",
      "parents": "NONE"
    },
    {
      "classType": "Atom",
      "ui": "A0404576",
      "sourceDescriptor": "NONE",
      "sourceConcept": "NONE",
      "concept": "https://uts-ws.nlm.nih.gov/rest/content/2026AA/CUI/C0235397",
      "suppressible": "false",
      "obsolete": "false",
      "rootSource": "CST",
      "termType": "GT",
      "code": "https://uts-ws.nlm.nih.gov/rest/content/2026AA/source/CST/DIABETES MELL",
      "language": "ENG",
      "name": "DIABETES MELLITUS PRECIPITATED",
      "ancestors": "NONE",
      "descendants": "NONE",
      "attributes": "NONE",
      "relations": "https://uts-ws.nlm.nih.gov/rest/content/2026AA/AUI/A0404576/relations",
      "children": "NONE",
      "parents": "NONE"
    },
    {
      "classType": "Atom",
      "ui": "A0404577",
      "sourceDescriptor": "NONE",
      "sourceConcept": "NONE",
      "concept": "https://uts-ws.nlm.nih.gov/rest/content/2026AA/CUI/C0235397",
      "suppressible": "false",
      "obsolete": "false",
      "rootSource": "WHO",
      "termType": "IT",
      "code": "https://uts-ws.nlm.nih.gov/rest/content/2026AA/source/WHO/0371",
      "language": "ENG",
      "name": "DIABETES MELLITUS PRECIPITATED",
      "ancestors": "NONE",
      "descendants": "NONE",
      "attributes": "NONE",
      "relations": "https://uts-ws.nlm.nih.gov/rest/content/2026AA/AUI/A0404577/relations",
      "children": "NONE",
      "parents": "NONE"
    },
    {
      "classType": "Atom",
      "ui": "A35899914",
      "sourceDescriptor": "https://uts-ws.nlm.nih.gov/rest/content/2026AA/source/MDREST/10012601",
      "sourceConcept": "NONE",
      "concept": "https://uts-ws.nlm.nih.gov/rest/content/2026AA/CUI/C0235397",
      "suppressible": "false",
      "obsolete": "false",
      "rootSource": "MDREST",
      "termType": "LLT",
      "code": "https://uts-ws.nlm.nih.gov/rest/content/2026AA/source/MDREST/10012620",
      "language": "EST",
      "name": "Äkkdiabeet",
      "ancestors": "NONE",
      "descendants": "NONE",
      "attributes": "NONE",
      "relations": "https://uts-ws.nlm.nih.gov/rest/content/2026AA/AUI/A35899914/relations",
      "children": "NONE",
      "parents": "NONE"
    },
    {
      "classType": "Atom",
      "ui": "A36105526",
      "sourceDescriptor": "https://uts-ws.nlm.nih.gov/rest/content/2026AA/source/MDRFIN/10012601",
      "sourceConcept": "NONE",
      "concept": "https://uts-ws.nlm.nih.gov/rest/content/2026AA/CUI/C0235397",
      "suppressible": "false",
      "obsolete": "false",
      "rootSource": "MDRFIN",
      "termType": "LLT",
      "code": "https://uts-ws.nlm.nih.gov/rest/content/2026AA/source/MDRFIN/10012620",
      "language": "FIN",
      "name": "Diabeteksen eteneminen",
      "ancestors": "NONE",
      "descendants": "NONE",
      "attributes": "NONE",
      "relations": "https://uts-ws.nlm.nih.gov/rest/content/2026AA/AUI/A36105526/relations",
      "children": "NONE",
      "parents": "NONE"
    },
    {
      "classType": "Atom",
      "ui": "A25970159",
      "sourceDescriptor": "https://uts-ws.nlm.nih.gov/rest/content/2026AA/source/MDRFRE/10012601",
      "sourceConcept": "NONE",
      "concept": "https://uts-ws.nlm.nih.gov/rest/content/2026AA/CUI/C0235397",
      "suppressible": "false",
      "obsolete": "false",
      "rootSource": "MDRFRE",
      "termType": "LLT",
      "code": "https://uts-ws.nlm.nih.gov/rest/content/2026AA/source/MDRFRE/10012620",
      "language": "FRE",
      "name": "Diabète sucré précipité",
      "ancestors": "NONE",
      "descendants": "NONE",
      "attributes": "NONE",
      "relations": "https://uts-ws.nlm.nih.gov/rest/content/2026AA/AUI/A25970159/relations",
      "children": "NONE",
      "parents": "NONE"
    },
    {
      "classType": "Atom",
      "ui": "A1436922",
      "sourceDescriptor": "NONE",
      "sourceConcept": "NONE",
      "concept": "https://uts-ws.nlm.nih.gov/rest/content/2026AA/CUI/C0235397",
      "suppressible": "false",
      "obsolete": "false",
      "rootSource": "WHOFRE",
      "termType": "IT",
      "code": "https://uts-ws.nlm.nih.gov/rest/content/2026AA/source/WHOFRE/0371",
      "language": "FRE",
      "name": "DIABETE SUCRE PROVOQUE",
      "ancestors": "NONE",
      "descendants": "NONE",
      "attributes": "NONE",
      "relations": "NONE",
      "children": "NONE",
      "parents": "NONE"
    },
    {
      "classType": "Atom",
      "ui": "A25812579",
      "sourceDescriptor": "https://uts-ws.nlm.nih.gov/rest/content/2026AA/source/MDRGER/10012601",
      "sourceConcept": "NONE",
      "concept": "https://uts-ws.nlm.nih.gov/rest/content/2026AA/CUI/C0235397",
      "suppressible": "false",
      "obsolete": "false",
      "rootSource": "MDRGER",
      "termType": "LLT",
      "code": "https://uts-ws.nlm.nih.gov/rest/content/2026AA/source/MDRGER/10012620",
      "language": "GER",
      "name": "Diabetes mellitus praezipitiert",
      "ancestors": "NONE",
      "descendants": "NONE",
      "attributes": "NONE",
      "relations": "https://uts-ws.nlm.nih.gov/rest/content/2026AA/AUI/A25812579/relations",
      "children": "NONE",
      "parents": "NONE"
    },
    {
      "classType": "Atom",
      "ui": "A1436927",
      "sourceDescriptor": "NONE",
      "sourceConcept": "NONE",
      "concept": "https://uts-ws.nlm.nih.gov/rest/content/2026AA/CUI/C0235397",
      "suppressible": "false",
      "obsolete": "false",
      "rootSource": "WHOGER",
      "termType": "IT",
      "code": "https://uts-ws.nlm.nih.gov/rest/content/2026AA/source/WHOGER/0371",
      "language": "GER",
      "name": "DIABETES MELLITUS AUSGELOEST",
      "ancestors": "NONE",
      "descendants": "NONE",
      "attributes": "NONE",
      "relations": "NONE",
      "children": "NONE",
      "parents": "NONE"
    },
    {
      "classType": "Atom",
      "ui": "A35150930",
      "sourceDescriptor": "https://uts-ws.nlm.nih.gov/rest/content/2026AA/source/MDRGRE/10012601",
      "sourceConcept": "NONE",
      "concept": "https://uts-ws.nlm.nih.gov/rest/content/2026AA/CUI/C0235397",
      "suppressible": "false",
      "obsolete": "false",
      "rootSource": "MDRGRE",
      "termType": "LLT",
      "code": "https://uts-ws.nlm.nih.gov/rest/content/2026AA/source/MDRGRE/10012620",
      "language": "GRE",
      "name": "Σακχαρώδης διαβήτης εσπευσμένος",
      "ancestors": "NONE",
      "descendants": "NONE",
      "attributes": "NONE",
      "relations": "https://uts-ws.nlm.nih.gov/rest/content/2026AA/AUI/A35150930/relations",
      "children": "NONE",
      "parents": "NONE"
    },
    {
      "classType": "Atom",
      "ui": "A26152704",
      "sourceDescriptor": "https://uts-ws.nlm.nih.gov/rest/content/2026AA/source/MDRHUN/10012601",
      "sourceConcept": "NONE",
      "concept": "https://uts-ws.nlm.nih.gov/rest/content/2026AA/CUI/C0235397",
      "suppressible": "false",
      "obsolete": "false",
      "rootSource": "MDRHUN",
      "termType": "LLT",
      "code": "https://uts-ws.nlm.nih.gov/rest/content/2026AA/source/MDRHUN/10012620",
      "language": "HUN",
      "name": "Indukált diabetes mellitus",
      "ancestors": "NONE",
      "descendants": "NONE",
      "attributes": "NONE",
      "relations": "https://uts-ws.nlm.nih.gov/rest/content/2026AA/AUI/A26152704/relations",
      "children": "NONE",
      "parents": "NONE"
    },
    {
      "classType": "Atom",
      "ui": "A37103492",
      "sourceDescriptor": "https://uts-ws.nlm.nih.gov/rest/content/2026AA/source/MDRISL/10012601",
      "sourceConcept": "NONE",
      "concept": "https://uts-ws.nlm.nih.gov/rest/content/2026AA/CUI/C0235397",
      "suppressible": "false",
      "obsolete": "false",
      "rootSource": "MDRISL",
      "termType": "LLT",
      "code": "https://uts-ws.nlm.nih.gov/rest/content/2026AA/source/MDRISL/10012620",
      "language": "ISL",
      "name": "Sykursýki kom út",
      "ancestors": "NONE",
      "descendants": "NONE",
      "attributes": "NONE",
      "relations": "https://uts-ws.nlm.nih.gov/rest/content/2026AA/AUI/A37103492/relations",
      "children": "NONE",
      "parents": "NONE"
    },
    {
      "classType": "Atom",
      "ui": "A25845677",
      "sourceDescriptor": "https://uts-ws.nlm.nih.gov/rest/content/2026AA/source/MDRITA/10012601",
      "sourceConcept": "NONE",
      "concept": "https://uts-ws.nlm.nih.gov/rest/content/2026AA/CUI/C0235397",
      "suppressible": "false",
      "obsolete": "false",
      "rootSource": "MDRITA",
      "termType": "LLT",
      "code": "https://uts-ws.nlm.nih.gov/rest/content/2026AA/source/MDRITA/10012620",
      "language": "ITA",
      "name": "Diabete mellito precipitato",
      "ancestors": "NONE",
      "descendants": "NONE",
      "attributes": "NONE",
      "relations": "https://uts-ws.nlm.nih.gov/rest/content/2026AA/AUI/A25845677/relations",
      "children": "NONE",
      "parents": "NONE"
    },
    {
      "classType": "Atom",
      "ui": "A31305443",
      "sourceDescriptor": "https://uts-ws.nlm.nih.gov/rest/content/2026AA/source/MDRKOR/10012601",
      "sourceConcept": "NONE",
      "concept": "https://uts-ws.nlm.nih.gov/rest/content/2026AA/CUI/C0235397",
      "suppressible": "false",
      "obsolete": "false",
      "rootSource": "MDRKOR",
      "termType": "LLT",
      "code": "https://uts-ws.nlm.nih.gov/rest/content/2026AA/source/MDRKOR/10012620",
      "language": "KOR",
      "name": "촉진된 당뇨병",
      "ancestors": "NONE",
      "descendants": "NONE",
      "attributes": "NONE",
      "relations": "https://uts-ws.nlm.nih.gov/rest/content/2026AA/AUI/A31305443/relations",
      "children": "NONE",
      "parents": "NONE"
    },
    {
      "classType": "Atom",
      "ui": "A34603341",
      "sourceDescriptor": "https://uts-ws.nlm.nih.gov/rest/content/2026AA/source/MDRLAV/10012601",
      "sourceConcept": "NONE",
      "concept": "https://uts-ws.nlm.nih.gov/rest/content/2026AA/CUI/C0235397",
      "suppressible": "false",
      "obsolete": "false",
      "rootSource": "MDRLAV",
      "termType": "LLT",
      "code": "https://uts-ws.nlm.nih.gov/rest/content/2026AA/source/MDRLAV/10012620",
      "language": "LAV",
      "name": "Cukura diabēta paasināšanās",
      "ancestors": "NONE",
      "descendants": "NONE",
      "attributes": "NONE",
      "relations": "https://uts-ws.nlm.nih.gov/rest/content/2026AA/AUI/A34603341/relations",
      "children": "NONE",
      "parents": "NONE"
    },
    {
      "classType": "Atom",
      "ui": "A36594571",
      "sourceDescriptor": "https://uts-ws.nlm.nih.gov/rest/content/2026AA/source/MDRLIT/10012601",
      "sourceConcept": "NONE",
      "concept": "https://uts-ws.nlm.nih.gov/rest/content/2026AA/CUI/C0235397",
      "suppressible": "false",
      "obsolete": "false",
      "rootSource": "MDRLIT",
      "termType": "LLT",
      "code": "https://uts-ws.nlm.nih.gov/rest/content/2026AA/source/MDRLIT/10012620",
      "language": "LIT",
      "name": "Cukrinio diabeto paūmėjimas",
      "ancestors": "NONE",
      "descendants": "NONE",
      "attributes": "NONE",
      "relations": "https://uts-ws.nlm.nih.gov/rest/content/2026AA/AUI/A36594571/relations",
      "children": "NONE",
      "parents": "NONE"
    },
    {
      "classType": "Atom",
      "ui": "A38066576",
      "sourceDescriptor": "https://uts-ws.nlm.nih.gov/rest/content/2026AA/source/MDRNOR/10012601",
      "sourceConcept": "NONE",
      "concept": "https://uts-ws.nlm.nih.gov/rest/content/2026AA/CUI/C0235397",
      "suppressible": "false",
      "obsolete": "false",
      "rootSource": "MDRNOR",
      "termType": "LLT",
      "code": "https://uts-ws.nlm.nih.gov/rest/content/2026AA/source/MDRNOR/10012620",
      "language": "NOR",
      "name": "Diabetes mellitus, fremkalt",
      "ancestors": "NONE",
      "descendants": "NONE",
      "attributes": "NONE",
      "relations": "https://uts-ws.nlm.nih.gov/rest/content/2026AA/AUI/A38066576/relations",
      "children": "NONE",
      "parents": "NONE"
    },
    {
      "classType": "Atom",
      "ui": "A35133945",
      "sourceDescriptor": "https://uts-ws.nlm.nih.gov/rest/content/2026AA/source/MDRPOL/10012601",
      "sourceConcept": "NONE",
      "concept": "https://uts-ws.nlm.nih.gov/rest/content/2026AA/CUI/C0235397",
      "suppressible": "false",
      "obsolete": "false",
      "rootSource": "MDRPOL",
      "termType": "LLT",
      "code": "https://uts-ws.nlm.nih.gov/rest/content/2026AA/source/MDRPOL/10012620",
      "language": "POL",
      "name": "Cukrzyca przyspieszona",
      "ancestors": "NONE",
      "descendants": "NONE",
      "attributes": "NONE",
      "relations": "https://uts-ws.nlm.nih.gov/rest/content/2026AA/AUI/A35133945/relations",
      "children": "NONE",
      "parents": "NONE"
    },
    {
      "classType": "Atom",
      "ui": "A32124696",
      "sourceDescriptor": "https://uts-ws.nlm.nih.gov/rest/content/2026AA/source/MDRBPO/10012601",
      "sourceConcept": "NONE",
      "concept": "https://uts-ws.nlm.nih.gov/rest/content/2026AA/CUI/C0235397",
      "suppressible": "false",
      "obsolete": "false",
      "rootSource": "MDRBPO",
      "termType": "LLT",
      "code": "https://uts-ws.nlm.nih.gov/rest/content/2026AA/source/MDRBPO/10012620",
      "language": "POR",
      "name": "Diabetes mellitus precipitado",
      "ancestors": "NONE",
      "descendants": "NONE",
      "attributes": "NONE",
      "relations": "https://uts-ws.nlm.nih.gov/rest/content/2026AA/AUI/A32124696/relations",
      "children": "NONE",
      "parents": "NONE"
    },
    {
      "classType": "Atom",
      "ui": "A1454887",
      "sourceDescriptor": "NONE",
      "sourceConcept": "NONE",
      "concept": "https://uts-ws.nlm.nih.gov/rest/content/2026AA/CUI/C0235397",
      "suppressible": "false",
      "obsolete": "false",
      "rootSource": "WHOPOR",
      "termType": "IT",
      "code": "https://uts-ws.nlm.nih.gov/rest/content/2026AA/source/WHOPOR/0371",
      "language": "POR",
      "name": "INDUCAO DE DIABETES MELLITUS",
      "ancestors": "NONE",
      "descendants": "NONE",
      "attributes": "NONE",
      "relations": "NONE",
      "children": "NONE",
      "parents": "NONE"
    },
    {
      "classType": "Atom",
      "ui": "A26380869",
      "sourceDescriptor": "https://uts-ws.nlm.nih.gov/rest/content/2026AA/source/MDRPOR/10012601",
      "sourceConcept": "NONE",
      "concept": "https://uts-ws.nlm.nih.gov/rest/content/2026AA/CUI/C0235397",
      "suppressible": "false",
      "obsolete": "false",
      "rootSource": "MDRPOR",
      "termType": "LLT",
      "code": "https://uts-ws.nlm.nih.gov/rest/content/2026AA/source/MDRPOR/10012620",
      "language": "POR",
      "name": "Diabetes mellitus precipitada",
      "ancestors": "NONE",
      "descendants": "NONE",
      "attributes": "NONE",
      "relations": "https://uts-ws.nlm.nih.gov/rest/content/2026AA/AUI/A26380869/relations",
      "children": "NONE",
      "parents": "NONE"
    },
    {
      "classType": "Atom",
      "ui": "A30778304",
      "sourceDescriptor": "https://uts-ws.nlm.nih.gov/rest/content/2026AA/source/MDRRUS/10012601",
      "sourceConcept": "NONE",
      "concept": "https://uts-ws.nlm.nih.gov/rest/content/2026AA/CUI/C0235397",
      "suppressible": "false",
      "obsolete": "false",
      "rootSource": "MDRRUS",
      "termType": "LLT",
      "code": "https://uts-ws.nlm.nih.gov/rest/content/2026AA/source/MDRRUS/10012620",
      "language": "RUS",
      "name": "Индуцированный сахарный диабет",
      "ancestors": "NONE",
      "descendants": "NONE",
      "attributes": "NONE",
      "relations": "https://uts-ws.nlm.nih.gov/rest/content/2026AA/AUI/A30778304/relations",
      "children": "NONE",
      "parents": "NONE"
    }
  ]
}