{
  "pageSize": 25,
  "pageNumber": 1,
  "pageCount": 1,
  "result": [
    {
      "classType": "Atom",
      "ui": "A8373437",
      "sourceDescriptor": "https://uts-ws.nlm.nih.gov/rest/content/2026AA/source/MTHICD9/250.0",
      "sourceConcept": "NONE",
      "concept": "https://uts-ws.nlm.nih.gov/rest/content/2026AA/CUI/C0865162",
      "suppressible": "false",
      "obsolete": "false",
      "rootSource": "MTHICD9",
      "termType": "ET",
      "code": "https://uts-ws.nlm.nih.gov/rest/content/2026AA/source/MTHICD9/250.0",
      "language": "ENG",
      "name": "Diabetes mellitus without mention of complication or manifestation",
      "ancestors": "NONE",
      "descendants": "NONE",
      "attributes": "NONE",
      "relations": "NONE",
      "children": "NONE",
      "parents": "NONE"
    }
  ]
}