{
  "pageSize": 25,
  "pageNumber": 74,
  "pageCount": 101,
  "result": [
    {
      "ui": "R161138718",
      "suppressible": false,
      "sourceUi": "NONE",
      "obsolete": false,
      "sourceOriginated": false,
      "rootSource": "MDRPOR",
      "groupId": "NONE",
      "attributeCount": 0,
      "classType": "AtomRelation",
      "relatedFromId": "https://uts-ws.nlm.nih.gov/rest/content/2026AA/AUI/A6368762",
      "relatedFromIdName": "Diabetes mellitus",
      "relationLabel": "RQ",
      "additionalRelationLabel": "classifies",
      "relatedId": "https://uts-ws.nlm.nih.gov/rest/content/2026AA/AUI/A26350757",
      "relatedIdName": "Diabetes mellitus reactivada"
    },
    {
      "ui": "R175420662",
      "suppressible": false,
      "sourceUi": "NONE",
      "obsolete": false,
      "sourceOriginated": false,
      "rootSource": "MDRCZE",
      "groupId": "NONE",
      "attributeCount": 0,
      "classType": "AtomRelation",
      "relatedFromId": "https://uts-ws.nlm.nih.gov/rest/content/2026AA/AUI/A15791577",
      "relatedFromIdName": "Diabetes mellitus",
      "relationLabel": "RQ",
      "additionalRelationLabel": "classifies",
      "relatedId": "https://uts-ws.nlm.nih.gov/rest/content/2026AA/AUI/A28712523",
      "relatedIdName": "Reaktivace diabetes mellitus"
    },
    {
      "ui": "R184452618",
      "suppressible": false,
      "sourceUi": "NONE",
      "obsolete": false,
      "sourceOriginated": false,
      "rootSource": "MDRRUS",
      "groupId": "NONE",
      "attributeCount": 0,
      "classType": "AtomRelation",
      "relatedFromId": "https://uts-ws.nlm.nih.gov/rest/content/2026AA/AUI/A30767719",
      "relatedFromIdName": "Сахарный диабет",
      "relationLabel": "RQ",
      "additionalRelationLabel": "classifies",
      "relatedId": "https://uts-ws.nlm.nih.gov/rest/content/2026AA/AUI/A30808569",
      "relatedIdName": "Сахарный диабет, реактивация"
    },
    {
      "ui": "R189884080",
      "suppressible": false,
      "sourceUi": "NONE",
      "obsolete": false,
      "sourceOriginated": false,
      "rootSource": "MDRKOR",
      "groupId": "NONE",
      "attributeCount": 0,
      "classType": "AtomRelation",
      "relatedFromId": "https://uts-ws.nlm.nih.gov/rest/content/2026AA/AUI/A31264400",
      "relatedFromIdName": "당뇨병",
      "relationLabel": "RQ",
      "additionalRelationLabel": "classifies",
      "relatedId": "https://uts-ws.nlm.nih.gov/rest/content/2026AA/AUI/A31321934",
      "relatedIdName": "재활성화된 당뇨병"
    },
    {
      "ui": "R197363904",
      "suppressible": false,
      "sourceUi": "NONE",
      "obsolete": false,
      "sourceOriginated": false,
      "rootSource": "MDRBPO",
      "groupId": "NONE",
      "attributeCount": 0,
      "classType": "AtomRelation",
      "relatedFromId": "https://uts-ws.nlm.nih.gov/rest/content/2026AA/AUI/A32235379",
      "relatedFromIdName": "Diabetes mellitus",
      "relationLabel": "RQ",
      "additionalRelationLabel": "classifies",
      "relatedId": "https://uts-ws.nlm.nih.gov/rest/content/2026AA/AUI/A32218119",
      "relatedIdName": "Diabetes mellitus reativado"
    },
    {
      "ui": "R210294924",
      "suppressible": false,
      "sourceUi": "NONE",
      "obsolete": false,
      "sourceOriginated": false,
      "rootSource": "MDRSWE",
      "groupId": "NONE",
      "attributeCount": 0,
      "classType": "AtomRelation",
      "relatedFromId": "https://uts-ws.nlm.nih.gov/rest/content/2026AA/AUI/A34440710",
      "relatedFromIdName": "Diabetes mellitus",
      "relationLabel": "RQ",
      "additionalRelationLabel": "classifies",
      "relatedId": "https://uts-ws.nlm.nih.gov/rest/content/2026AA/AUI/A34562170",
      "relatedIdName": "Återaktiverad diabetes mellitus"
    },
    {
      "ui": "R209824641",
      "suppressible": false,
      "sourceUi": "NONE",
      "obsolete": false,
      "sourceOriginated": false,
      "rootSource": "MDRLAV",
      "groupId": "NONE",
      "attributeCount": 0,
      "classType": "AtomRelation",
      "relatedFromId": "https://uts-ws.nlm.nih.gov/rest/content/2026AA/AUI/A34590749",
      "relatedFromIdName": "Cukura diabēts",
      "relationLabel": "RQ",
      "additionalRelationLabel": "classifies",
      "relatedId": "https://uts-ws.nlm.nih.gov/rest/content/2026AA/AUI/A34603342",
      "relatedIdName": "Cukura diabēta reaktivācija"
    },
    {
      "ui": "R212222657",
      "suppressible": false,
      "sourceUi": "NONE",
      "obsolete": false,
      "sourceOriginated": false,
      "rootSource": "MDRGRE",
      "groupId": "NONE",
      "attributeCount": 0,
      "classType": "AtomRelation",
      "relatedFromId": "https://uts-ws.nlm.nih.gov/rest/content/2026AA/AUI/A35148397",
      "relatedFromIdName": "Σακχαρώδης διαβήτης",
      "relationLabel": "RQ",
      "additionalRelationLabel": "classifies",
      "relatedId": "https://uts-ws.nlm.nih.gov/rest/content/2026AA/AUI/A35120651",
      "relatedIdName": "Σακχαρώδης διαβήτης επανενεργοποιημένος"
    },
    {
      "ui": "R212080290",
      "suppressible": false,
      "sourceUi": "NONE",
      "obsolete": false,
      "sourceOriginated": false,
      "rootSource": "MDRPOL",
      "groupId": "NONE",
      "attributeCount": 0,
      "classType": "AtomRelation",
      "relatedFromId": "https://uts-ws.nlm.nih.gov/rest/content/2026AA/AUI/A35002396",
      "relatedFromIdName": "Cukrzyca",
      "relationLabel": "RQ",
      "additionalRelationLabel": "classifies",
      "relatedId": "https://uts-ws.nlm.nih.gov/rest/content/2026AA/AUI/A35152766",
      "relatedIdName": "Reaktywacja cukrzycy"
    },
    {
      "ui": "R213571985",
      "suppressible": false,
      "sourceUi": "NONE",
      "obsolete": false,
      "sourceOriginated": false,
      "rootSource": "MDRARA",
      "groupId": "NONE",
      "attributeCount": 0,
      "classType": "AtomRelation",
      "relatedFromId": "https://uts-ws.nlm.nih.gov/rest/content/2026AA/AUI/A35328898",
      "relatedFromIdName": "مرض السكري",
      "relationLabel": "RQ",
      "additionalRelationLabel": "classifies",
      "relatedId": "https://uts-ws.nlm.nih.gov/rest/content/2026AA/AUI/A35288344",
      "relatedIdName": "إعادة تنشيط مرض السكري"
    },
    {
      "ui": "R218752501",
      "suppressible": false,
      "sourceUi": "NONE",
      "obsolete": false,
      "sourceOriginated": false,
      "rootSource": "MDREST",
      "groupId": "NONE",
      "attributeCount": 0,
      "classType": "AtomRelation",
      "relatedFromId": "https://uts-ws.nlm.nih.gov/rest/content/2026AA/AUI/A35912479",
      "relatedFromIdName": "Suhkurtõbi",
      "relationLabel": "RQ",
      "additionalRelationLabel": "classifies",
      "relatedId": "https://uts-ws.nlm.nih.gov/rest/content/2026AA/AUI/A35842099",
      "relatedIdName": "Reaktiveerunud suhkurtõbi"
    },
    {
      "ui": "R219934838",
      "suppressible": false,
      "sourceUi": "NONE",
      "obsolete": false,
      "sourceOriginated": false,
      "rootSource": "MDRFIN",
      "groupId": "NONE",
      "attributeCount": 0,
      "classType": "AtomRelation",
      "relatedFromId": "https://uts-ws.nlm.nih.gov/rest/content/2026AA/AUI/A36161206",
      "relatedFromIdName": "Diabetes mellitus",
      "relationLabel": "RQ",
      "additionalRelationLabel": "classifies",
      "relatedId": "https://uts-ws.nlm.nih.gov/rest/content/2026AA/AUI/A36148924",
      "relatedIdName": "Diabeteksen reaktivaatio"
    },
    {
      "ui": "R222145071",
      "suppressible": false,
      "sourceUi": "NONE",
      "obsolete": false,
      "sourceOriginated": false,
      "rootSource": "MDRHRV",
      "groupId": "NONE",
      "attributeCount": 0,
      "classType": "AtomRelation",
      "relatedFromId": "https://uts-ws.nlm.nih.gov/rest/content/2026AA/AUI/A36663076",
      "relatedFromIdName": "Dijabetes melitus",
      "relationLabel": "RQ",
      "additionalRelationLabel": "classifies",
      "relatedId": "https://uts-ws.nlm.nih.gov/rest/content/2026AA/AUI/A36605687",
      "relatedIdName": "Reaktivacija dijabetesa melitusa"
    },
    {
      "ui": "R221931051",
      "suppressible": false,
      "sourceUi": "NONE",
      "obsolete": false,
      "sourceOriginated": false,
      "rootSource": "MDRLIT",
      "groupId": "NONE",
      "attributeCount": 0,
      "classType": "AtomRelation",
      "relatedFromId": "https://uts-ws.nlm.nih.gov/rest/content/2026AA/AUI/A36578932",
      "relatedFromIdName": "Cukrinis diabetas",
      "relationLabel": "RQ",
      "additionalRelationLabel": "classifies",
      "relatedId": "https://uts-ws.nlm.nih.gov/rest/content/2026AA/AUI/A36719231",
      "relatedIdName": "Atsinaujinęs cukrinis diabetas"
    },
    {
      "ui": "R223728040",
      "suppressible": false,
      "sourceUi": "NONE",
      "obsolete": false,
      "sourceOriginated": false,
      "rootSource": "MDRISL",
      "groupId": "NONE",
      "attributeCount": 0,
      "classType": "AtomRelation",
      "relatedFromId": "https://uts-ws.nlm.nih.gov/rest/content/2026AA/AUI/A37120940",
      "relatedFromIdName": "Sykursýki",
      "relationLabel": "RQ",
      "additionalRelationLabel": "classifies",
      "relatedId": "https://uts-ws.nlm.nih.gov/rest/content/2026AA/AUI/A37058689",
      "relatedIdName": "Sykursýki endurvirkjað"
    },
    {
      "ui": "R228218099",
      "suppressible": false,
      "sourceUi": "NONE",
      "obsolete": false,
      "sourceOriginated": false,
      "rootSource": "MDRSLK",
      "groupId": "NONE",
      "attributeCount": 0,
      "classType": "AtomRelation",
      "relatedFromId": "https://uts-ws.nlm.nih.gov/rest/content/2026AA/AUI/A38023665",
      "relatedFromIdName": "Diabetes mellitus",
      "relationLabel": "RQ",
      "additionalRelationLabel": "classifies",
      "relatedId": "https://uts-ws.nlm.nih.gov/rest/content/2026AA/AUI/A37929132",
      "relatedIdName": "Exacerbovaný diabetes mellitus"
    },
    {
      "ui": "R227711832",
      "suppressible": false,
      "sourceUi": "NONE",
      "obsolete": false,
      "sourceOriginated": false,
      "rootSource": "MDRNOR",
      "groupId": "NONE",
      "attributeCount": 0,
      "classType": "AtomRelation",
      "relatedFromId": "https://uts-ws.nlm.nih.gov/rest/content/2026AA/AUI/A37846422",
      "relatedFromIdName": "Diabetes mellitus",
      "relationLabel": "RQ",
      "additionalRelationLabel": "classifies",
      "relatedId": "https://uts-ws.nlm.nih.gov/rest/content/2026AA/AUI/A38066577",
      "relatedIdName": "Reaktivert diabetes mellitus"
    },
    {
      "ui": "R227491176",
      "suppressible": false,
      "sourceUi": "NONE",
      "obsolete": false,
      "sourceOriginated": false,
      "rootSource": "MDRSLV",
      "groupId": "NONE",
      "attributeCount": 0,
      "classType": "AtomRelation",
      "relatedFromId": "https://uts-ws.nlm.nih.gov/rest/content/2026AA/AUI/A37958582",
      "relatedFromIdName": "Sladkorna bolezen",
      "relationLabel": "RQ",
      "additionalRelationLabel": "classifies",
      "relatedId": "https://uts-ws.nlm.nih.gov/rest/content/2026AA/AUI/A38154361",
      "relatedIdName": "Reaktivirana sladkorna bolezen"
    },
    {
      "ui": "R91966283",
      "suppressible": false,
      "sourceUi": "NONE",
      "obsolete": false,
      "sourceOriginated": false,
      "rootSource": "MTH",
      "groupId": "NONE",
      "attributeCount": 0,
      "classType": "ConceptRelation",
      "relationLabel": "RB",
      "additionalRelationLabel": "",
      "relatedId": "https://uts-ws.nlm.nih.gov/rest/content/2026AA/CUI/C0235399",
      "relatedIdName": "Diabetes mellitus reactivated"
    },
    {
      "ui": "R111776538",
      "suppressible": false,
      "sourceUi": "NONE",
      "obsolete": false,
      "sourceOriginated": false,
      "rootSource": "MSH",
      "groupId": "NONE",
      "attributeCount": 0,
      "classType": "AtomClusterRelation",
      "relatedFromId": "https://uts-ws.nlm.nih.gov/rest/content/2026AA/source/MSH/D003920",
      "relatedFromIdName": "Diabetes Mellitus",
      "relationLabel": "PAR",
      "additionalRelationLabel": "",
      "relatedId": "https://uts-ws.nlm.nih.gov/rest/content/2026AA/source/MSH/D056731",
      "relatedIdName": "Donohue Syndrome"
    },
    {
      "ui": "R113409250",
      "suppressible": false,
      "sourceUi": "NONE",
      "obsolete": false,
      "sourceOriginated": false,
      "rootSource": "MSHFRE",
      "groupId": "NONE",
      "attributeCount": 0,
      "classType": "AtomClusterRelation",
      "relatedFromId": "https://uts-ws.nlm.nih.gov/rest/content/2026AA/source/MSHFRE/D003920",
      "relatedFromIdName": "Diabète",
      "relationLabel": "PAR",
      "additionalRelationLabel": "",
      "relatedId": "https://uts-ws.nlm.nih.gov/rest/content/2026AA/source/MSHFRE/D056731",
      "relatedIdName": "Syndrome de Donohue"
    },
    {
      "ui": "R113429686",
      "suppressible": false,
      "sourceUi": "NONE",
      "obsolete": false,
      "sourceOriginated": false,
      "rootSource": "MSHGER",
      "groupId": "NONE",
      "attributeCount": 0,
      "classType": "AtomClusterRelation",
      "relatedFromId": "https://uts-ws.nlm.nih.gov/rest/content/2026AA/source/MSHGER/D003920",
      "relatedFromIdName": "Diabetes mellitus",
      "relationLabel": "PAR",
      "additionalRelationLabel": "",
      "relatedId": "https://uts-ws.nlm.nih.gov/rest/content/2026AA/source/MSHGER/D056731",
      "relatedIdName": "Donohue-Syndrom"
    },
    {
      "ui": "R113450190",
      "suppressible": false,
      "sourceUi": "NONE",
      "obsolete": false,
      "sourceOriginated": false,
      "rootSource": "MSHITA",
      "groupId": "NONE",
      "attributeCount": 0,
      "classType": "AtomClusterRelation",
      "relatedFromId": "https://uts-ws.nlm.nih.gov/rest/content/2026AA/source/MSHITA/D003920",
      "relatedFromIdName": "Diabete mellito",
      "relationLabel": "PAR",
      "additionalRelationLabel": "",
      "relatedId": "https://uts-ws.nlm.nih.gov/rest/content/2026AA/source/MSHITA/D056731",
      "relatedIdName": "Sindrome di Donohue"
    },
    {
      "ui": "R113472149",
      "suppressible": false,
      "sourceUi": "NONE",
      "obsolete": false,
      "sourceOriginated": false,
      "rootSource": "MSHPOR",
      "groupId": "NONE",
      "attributeCount": 0,
      "classType": "AtomClusterRelation",
      "relatedFromId": "https://uts-ws.nlm.nih.gov/rest/content/2026AA/source/MSHPOR/D003920",
      "relatedFromIdName": "Diabetes Mellitus",
      "relationLabel": "PAR",
      "additionalRelationLabel": "",
      "relatedId": "https://uts-ws.nlm.nih.gov/rest/content/2026AA/source/MSHPOR/D056731",
      "relatedIdName": "Síndrome de Donohue"
    },
    {
      "ui": "R113495535",
      "suppressible": false,
      "sourceUi": "NONE",
      "obsolete": false,
      "sourceOriginated": false,
      "rootSource": "MSHSPA",
      "groupId": "NONE",
      "attributeCount": 0,
      "classType": "AtomClusterRelation",
      "relatedFromId": "https://uts-ws.nlm.nih.gov/rest/content/2026AA/source/MSHSPA/D003920",
      "relatedFromIdName": "Diabetes Mellitus",
      "relationLabel": "PAR",
      "additionalRelationLabel": "",
      "relatedId": "https://uts-ws.nlm.nih.gov/rest/content/2026AA/source/MSHSPA/D056731",
      "relatedIdName": "Síndrome de Donohue"
    }
  ]
}