{
  "pageSize": 25,
  "pageNumber": 1,
  "pageCount": 1,
  "result": [
    {
      "classType": "Atom",
      "ui": "A13982762",
      "sourceDescriptor": "NONE",
      "sourceConcept": "https://uts-ws.nlm.nih.gov/rest/content/2026AA/source/MEDCIN/35007",
      "concept": "https://uts-ws.nlm.nih.gov/rest/content/2026AA/CUI/C0554876",
      "suppressible": "false",
      "obsolete": "false",
      "rootSource": "MEDCIN",
      "termType": "PT",
      "code": "https://uts-ws.nlm.nih.gov/rest/content/2026AA/source/MEDCIN/35007",
      "language": "ENG",
      "name": "poorly controlled diabetes mellitus",
      "ancestors": "NONE",
      "descendants": "NONE",
      "attributes": "https://uts-ws.nlm.nih.gov/rest/content/2026AA/AUI/A13982762/attributes",
      "relations": "NONE",
      "children": "NONE",
      "parents": "NONE"
    },
    {
      "classType": "Atom",
      "ui": "A18080507",
      "sourceDescriptor": "NONE",
      "sourceConcept": "NONE",
      "concept": "https://uts-ws.nlm.nih.gov/rest/content/2026AA/CUI/C0554876",
      "suppressible": "false",
      "obsolete": "false",
      "rootSource": "MTH",
      "termType": "PN",
      "code": "https://uts-ws.nlm.nih.gov/rest/content/2026AA/source/MTH/NOCODE",
      "language": "ENG",
      "name": "poorly controlled diabetes mellitus",
      "ancestors": "NONE",
      "descendants": "NONE",
      "attributes": "NONE",
      "relations": "NONE",
      "children": "NONE",
      "parents": "NONE"
    },
    {
      "classType": "Atom",
      "ui": "A27821784",
      "sourceDescriptor": "https://uts-ws.nlm.nih.gov/rest/content/2026AA/source/OMIM/MTHU056620",
      "sourceConcept": "NONE",
      "concept": "https://uts-ws.nlm.nih.gov/rest/content/2026AA/CUI/C0554876",
      "suppressible": "false",
      "obsolete": "false",
      "rootSource": "OMIM",
      "termType": "PTCS",
      "code": "https://uts-ws.nlm.nih.gov/rest/content/2026AA/source/OMIM/MTHU056620",
      "language": "ENG",
      "name": "Diabetes mellitus, poorly controlled",
      "ancestors": "https://uts-ws.nlm.nih.gov/rest/content/2026AA/AUI/A27821784/ancestors",
      "descendants": "NONE",
      "attributes": "NONE",
      "relations": "https://uts-ws.nlm.nih.gov/rest/content/2026AA/AUI/A27821784/relations",
      "children": "NONE",
      "parents": "https://uts-ws.nlm.nih.gov/rest/content/2026AA/AUI/A27821784/parents"
    },
    {
      "classType": "Atom",
      "ui": "A13817126",
      "sourceDescriptor": "NONE",
      "sourceConcept": "https://uts-ws.nlm.nih.gov/rest/content/2026AA/source/MEDCIN/35007",
      "concept": "https://uts-ws.nlm.nih.gov/rest/content/2026AA/CUI/C0554876",
      "suppressible": "false",
      "obsolete": "false",
      "rootSource": "MEDCIN",
      "termType": "SY",
      "code": "https://uts-ws.nlm.nih.gov/rest/content/2026AA/source/MEDCIN/35007",
      "language": "ENG",
      "name": "diabetes mellitus poorly controlled",
      "ancestors": "NONE",
      "descendants": "NONE",
      "attributes": "https://uts-ws.nlm.nih.gov/rest/content/2026AA/AUI/A13817126/attributes",
      "relations": "NONE",
      "children": "NONE",
      "parents": "NONE"
    },
    {
      "classType": "Atom",
      "ui": "A13633536",
      "sourceDescriptor": "NONE",
      "sourceConcept": "https://uts-ws.nlm.nih.gov/rest/content/2026AA/source/MEDCIN/35007",
      "concept": "https://uts-ws.nlm.nih.gov/rest/content/2026AA/CUI/C0554876",
      "suppressible": "false",
      "obsolete": "false",
      "rootSource": "MEDCIN",
      "termType": "FN",
      "code": "https://uts-ws.nlm.nih.gov/rest/content/2026AA/source/MEDCIN/35007",
      "language": "ENG",
      "name": "poorly controlled diabetes mellitus (diagnosis)",
      "ancestors": "NONE",
      "descendants": "NONE",
      "attributes": "NONE",
      "relations": "NONE",
      "children": "NONE",
      "parents": "NONE"
    }
  ]
}